<annotation>
	<folder>train</folder>
	<filename>mauve15.jpeg</filename>
	<path>C:\Users\hp\Documents\SJU\Spring '19\Senior Project\WAT Project\images\train\mauve15.jpeg</path>
	<source>
		<database>Unknown</database>
	</source>
	<size>
		<width>750</width>
		<height>361</height>
		<depth>3</depth>
	</size>
	<segmented>0</segmented>
	<object>
		<name>adidas Yeezy 700 Mauve</name>
		<pose>Unspecified</pose>
		<truncated>1</truncated>
		<difficult>0</difficult>
		<bndbox>
			<xmin>4</xmin>
			<ymin>2</ymin>
			<xmax>750</xmax>
			<ymax>356</ymax>
		</bndbox>
	</object>
</annotation>
